{
    "produtos": [
  {
    "id": "1",
    "titulo": "Tênis Nike Revolution \n6 Next Nature Masculino",
    "categoria": "Tênis",
    "preco": 250,
    "priceDiscount": 192,
    "img": "/air-branco.svg",
    "marca": "Nike",
    "reference": 24965421,
    "stars": 4.8,
    "rating": 260,
    "description": "Lorem ipsum dolor sit amet, consectetur adipiscing elit, sed do eiusmod tempor incididunt ut labore et dolore magna aliqua. Ut enim ad minim veniam, quis nostrud exercitation ullamco."
  },
  {
    "id": "2",
    "titulo": "Chuck Taylor All Star",
    "categoria": "Tênis",
    "preco": 240,
    "priceDiscount": 196,
    "img": "/sapato-all-star.png",
    "marca": "Converse",
    "reference": 24965422,
    "stars": 4.2,
    "rating": 84,
    "description": "Lorem ipsum dolor sit amet, consectetur adipiscing elit, sed do eiusmod tempor incididunt ut labore et dolore magna aliqua. Ut enim ad minim veniam, quis nostrud exercitation ullamco."
  },
  {
    "id": "3",
    "titulo": "K-Swiss V8 - Masculino",
    "categoria": "Tênis",
    "preco": 200,
    "img": "/tenis.svg",
    "marca": "K-SWISS",
    "reference": 24965423,
    "stars": 4.5,
    "rating": 52,
    "description": "Lorem ipsum dolor sit amet, consectetur adipiscing elit, sed do eiusmod tempor incididunt ut labore et dolore magna aliqua. Ut enim ad minim veniam, quis nostrud exercitation ullamco."
  },
  {
    "id": "4",
    "titulo": "K-Swiss V8 - Masculino",
    "categoria": "Tênis",
    "preco": 210,
    "img": "/tenis.svg",
    "marca": "K-SWISS",
    "reference": 24965424,
    "stars": 4.2,
    "rating": 35,
    "description": "Lorem ipsum dolor sit amet, consectetur adipiscing elit, sed do eiusmod tempor incididunt ut labore et dolore magna aliqua. Ut enim ad minim veniam, quis nostrud exercitation ullamco."
  },
  {
    "id": "5",
    "titulo": "K-Swiss V8 - Masculino",
    "categoria": "Tênis",
    "preco": 190,
    "priceDiscount": 165,
    "img": "/tenis.svg",
    "marca": "K-SWISS",
    "reference": 24965425,
    "stars": 2.5,
    "rating": 27,
    "description": "Lorem ipsum dolor sit amet, consectetur adipiscing elit, sed do eiusmod tempor incididunt ut labore et dolore magna aliqua. Ut enim ad minim veniam, quis nostrud exercitation ullamco."
  },
  {
    "id": "6",
    "titulo": "K-Swiss V8 - Masculino",
    "categoria": "Tênis",
    "preco": 200,
    "priceDiscount": 178,
    "img": "/tenis.svg",
    "marca": "K-SWISS",
    "reference": 24965426,
    "stars": 4.8,
    "rating": 81,
    "description": "Lorem ipsum dolor sit amet, consectetur adipiscing elit, sed do eiusmod tempor incididunt ut labore et dolore magna aliqua. Ut enim ad minim veniam, quis nostrud exercitation ullamco."
  },
  {
    "id": "7",
    "titulo": "K-Swiss V8 - Masculino",
    "categoria": "Tênis",
    "preco": 180,
    "img": "/tenis.svg",
    "marca": "K-SWISS",
    "reference": 24965427,
    "stars": 3.9,
    "rating": 33,
    "description": "Lorem ipsum dolor sit amet, consectetur adipiscing elit, sed do eiusmod tempor incididunt ut labore et dolore magna aliqua. Ut enim ad minim veniam, quis nostrud exercitation ullamco."
  },
  {
    "id": "8",
    "titulo": "K-Swiss V8 - Masculino",
    "categoria": "Tênis",
    "preco": 200,
    "img": "/tenis.svg",
    "marca": "K-SWISS",
    "reference": 24965428,
    "stars": 4.7,
    "rating": 68,
    "description": "Lorem ipsum dolor sit amet, consectetur adipiscing elit, sed do eiusmod tempor incididunt ut labore et dolore magna aliqua. Ut enim ad minim veniam, quis nostrud exercitation ullamco."
  },
  {
    "id": "9",
    "titulo": "K-Swiss V8 - Masculino",
    "categoria": "Tênis",
    "preco": 200,
    "img": "/tenis.svg",
    "marca": "K-SWISS",
    "reference": 24965429,
    "stars": 1.5,
    "rating": 18,
    "description": "Lorem ipsum dolor sit amet, consectetur adipiscing elit, sed do eiusmod tempor incididunt ut labore et dolore magna aliqua. Ut enim ad minim veniam, quis nostrud exercitation ullamco."
  },
  {
    "id": "10",
    "titulo": "K-Swiss V8 - Masculino",
    "categoria": "Tênis",
    "preco": 200,
    "priceDiscount": 150,
    "img": "/tenis.svg",
    "marca": "K-SWISS",
    "reference": 24965430,
    "stars": 2.5,
    "rating": 52,
    "description": "Lorem ipsum dolor sit amet, consectetur adipiscing elit, sed do eiusmod tempor incididunt ut labore et dolore magna aliqua. Ut enim ad minim veniam, quis nostrud exercitation ullamco."
  },
  {
    "id": "11",
    "titulo": "K-Swiss V8 - Masculino",
    "categoria": "Tênis",
    "preco": 200,
    "img": "/tenis.svg",
    "marca": "K-SWISS",
    "reference": 24965431,
    "stars": 4.6,
    "rating": 42,
    "description": "Lorem ipsum dolor sit amet, consectetur adipiscing elit, sed do eiusmod tempor incididunt ut labore et dolore magna aliqua. Ut enim ad minim veniam, quis nostrud exercitation ullamco."
  },
  {
    "id": "12",
    "titulo": "K-Swiss V8 - Masculino",
    "categoria": "Tênis",
    "preco": 200,
    "priceDiscount": 178,
    "img": "/tenis.svg",
    "marca": "K-SWISS",
    "reference": 24965432,
    "stars": 4.8,
    "rating": 12,
    "description": "Lorem ipsum dolor sit amet, consectetur adipiscing elit, sed do eiusmod tempor incididunt ut labore et dolore magna aliqua. Ut enim ad minim veniam, quis nostrud exercitation ullamco."
  },
  {
    "id": "13",
    "titulo": "K-Swiss V8 - Masculino",
    "categoria": "Tênis",
    "preco": 200,
    "img": "/tenis.svg",
    "marca": "K-SWISS",
    "reference": 24965433,
    "stars": 3.7,
    "rating": 16,
    "description": "Lorem ipsum dolor sit amet, consectetur adipiscing elit, sed do eiusmod tempor incididunt ut labore et dolore magna aliqua. Ut enim ad minim veniam, quis nostrud exercitation ullamco."
  },
  {
    "id": "14",
    "titulo": "K-Swiss V8 - Masculino",
    "categoria": "Tênis",
    "preco": 200,
    "priceDiscount": 180,
    "img": "/tenis.svg",
    "marca": "K-SWISS",
    "reference": 24965434,
    "stars": 4.8,
    "rating": 18,
    "description": "Lorem ipsum dolor sit amet, consectetur adipiscing elit, sed do eiusmod tempor incididunt ut labore et dolore magna aliqua. Ut enim ad minim veniam, quis nostrud exercitation ullamco."
  },
  {
    "id": "15",
    "titulo": "K-Swiss V8 - Masculino",
    "categoria": "Tênis",
    "preco": 200,
    "priceDiscount": 166,
    "img": "/tenis.svg",
    "marca": "K-SWISS",
    "reference": 24965435,
    "stars": 4.7,
    "rating": 11,
    "description": "Lorem ipsum dolor sit amet, consectetur adipiscing elit, sed do eiusmod tempor incididunt ut labore et dolore magna aliqua. Ut enim ad minim veniam, quis nostrud exercitation ullamco."
  },
  {
    "id": "16",
    "titulo": "K-Swiss V8 - Masculino",
    "categoria": "Tênis",
    "preco": 200,
    "img": "/tenis.svg",
    "marca": "K-SWISS",
    "reference": 24965436,
    "stars": 1.8,
    "rating": 21,
    "description": "Lorem ipsum dolor sit amet, consectetur adipiscing elit, sed do eiusmod tempor incididunt ut labore et dolore magna aliqua. Ut enim ad minim veniam, quis nostrud exercitation ullamco."
  },
  {
    "id": "17",
    "titulo": "K-Swiss V8 - Masculino",
    "categoria": "Tênis",
    "preco": 200,
    "priceDiscount": 176,
    "img": "/tenis.svg",
    "marca": "K-SWISS",
    "reference": 24965437,
    "stars": 4.1,
    "rating": 56,
    "description": "Lorem ipsum dolor sit amet, consectetur adipiscing elit, sed do eiusmod tempor incididunt ut labore et dolore magna aliqua. Ut enim ad minim veniam, quis nostrud exercitation ullamco."
  },
  {
    "id": "18",
    "titulo": "Baby Reborn",
    "categoria": "Família",
    "preco": 3850,
    "priceDiscount": 2860,
    "img": "/baby-reborn.png",
    "marca": "Reborn Babe",
    "reference": 24965438,
    "stars": 4.9,
    "rating": 524,
    "description": "Lorem ipsum dolor sit amet, consectetur adipiscing elit, sed do eiusmod tempor incididunt ut labore et dolore magna aliqua. Ut enim ad minim veniam, quis nostrud exercitation ullamco."
  },
  {
    "id": "19",
    "titulo": "K-Swiss V8 - Masculino",
    "categoria": "Tênis",
    "preco": 200,
    "priceDiscount": 171,
    "img": "/tenis.svg",
    "marca": "K-SWISS",
    "reference": 24965439,
    "stars": 3.8,
    "rating": 8,
    "description": "Lorem ipsum dolor sit amet, consectetur adipiscing elit, sed do eiusmod tempor incididunt ut labore et dolore magna aliqua. Ut enim ad minim veniam, quis nostrud exercitation ullamco."
  },
  {
    "id": "20",
    "titulo": "K-Swiss V8 - Masculino",
    "categoria": "Tênis",
    "preco": 200,
    "img": "/tenis.svg",
    "marca": "K-SWISS",
    "reference": 24965440,
    "stars": 4.4,
    "rating": 6,
    "description": "Lorem ipsum dolor sit amet, consectetur adipiscing elit, sed do eiusmod tempor incididunt ut labore et dolore magna aliqua. Ut enim ad minim veniam, quis nostrud exercitation ullamco."
  }
]

  }
